spacekernel-0.1.0.dev9.dist-info/RECORD
spacekernel-0.1.0.dev9.dist-info/WHEEL
spacekernel-0.1.0.dev9.dist-info/top_level.txt
spacekernel-0.1.0.dev9.dist-info/METADATA
spacekernel-0.1.0.dev9.dist-info/licenses/LICENSE
spacekernel-0.1.0.dev9.dist-info/licenses/LICENSE-SOFA.txt
spacekernel-0.1.0.dev9.dist-info/licenses/LICENSE-SGP4.txt
spacekernel/__init__.pxd
spacekernel/constants.py
spacekernel/__init__.py
spacekernel/typing.py
spacekernel/bodies/bodies.pyi
spacekernel/bodies/__init__.pxd
spacekernel/bodies/bodies.pxd
spacekernel/bodies/__init__.py
spacekernel/bodies/bodies.cpython-312-darwin.so
spacekernel/bodies/bodies.c
spacekernel/ccsds/__init__.py
spacekernel/od/__init__.pxd
spacekernel/od/__init__.py
spacekernel/od/sgp4dc/wrapper.pxd
spacekernel/od/sgp4dc/__init__.pxd
spacekernel/od/sgp4dc/__init__.py
spacekernel/frames/rotations.c
spacekernel/frames/frames.pyi
spacekernel/frames/__init__.pxd
spacekernel/frames/geocentric.c
spacekernel/frames/__init__.py
spacekernel/frames/frames.pxd
spacekernel/frames/frames.c
spacekernel/frames/transform.pxd
spacekernel/frames/rotations.cpython-312-darwin.so
spacekernel/frames/frames.cpython-312-darwin.so
spacekernel/frames/rotations.pxd
spacekernel/frames/geocentric.pxd
spacekernel/frames/geocentric.cpython-312-darwin.so
spacekernel/frames/geocentric.pyi
spacekernel/frames/rotations.pyi
spacekernel/frames/transform.pyi
spacekernel/utils/settings.json
spacekernel/utils/__init__.pxd
spacekernel/utils/__init__.py
spacekernel/utils/representable.pxd
spacekernel/utils/representable.cpython-312-darwin.so
spacekernel/utils/representable.c
spacekernel/utils/representable.pyi
spacekernel/state/ephemeris.pyi
spacekernel/state/state.pyi
spacekernel/state/state.c
spacekernel/state/state.pxd
spacekernel/state/__init__.pxd
spacekernel/state/ephemeris.pxd
spacekernel/state/__init__.py
spacekernel/state/coe.c
spacekernel/state/ephemeris.cpython-312-darwin.so
spacekernel/state/coe.pxd
spacekernel/state/coe.pyi
spacekernel/state/coe.cpython-312-darwin.so
spacekernel/state/ephemeris.c
spacekernel/state/state.cpython-312-darwin.so
spacekernel/time/format.cpython-312-darwin.so
spacekernel/time/format.pxd
spacekernel/time/format.c
spacekernel/time/format.pyi
spacekernel/time/__init__.pxd
spacekernel/time/__init__.py
