Metadata-Version: 2.4
Name: spacekernel
Version: 0.1.0.dev9
Summary: The Core Engine for Space Mission Simulation and Analysis
Author-email: "Rafael R. L. Benevides" <rafael.rl.benevides@gmail.com>
License-Expression: BSD-3-Clause
Project-URL: Homepage, https://github.com/spacekernel/spacekernel
Project-URL: Documentation, https://spacekernel.github.io
Keywords: satellite,orbit,astrodynamics,SSA,RPO,SGP4
Classifier: Development Status :: 3 - Alpha
Classifier: Intended Audience :: Science/Research
Classifier: Intended Audience :: Developers
Classifier: Intended Audience :: Telecommunications Industry
Classifier: Topic :: Scientific/Engineering :: Astronomy
Classifier: Programming Language :: Python :: 3.10
Classifier: Programming Language :: Python :: 3.11
Classifier: Programming Language :: Python :: 3.12
Classifier: Programming Language :: Python :: 3.13
Requires-Python: >=3.11
License-File: LICENSE
License-File: LICENSE-SGP4.txt
License-File: LICENSE-SOFA.txt
Requires-Dist: requests
Requires-Dist: numpy
Requires-Dist: scipy
Requires-Dist: pandas
Requires-Dist: scikit-learn
Requires-Dist: matplotlib
Requires-Dist: PyQt5
Requires-Dist: pyvista
Dynamic: license-file
